LICENSE
setup.py
work_wechat_sdk/__init__.py
work_wechat_sdk/appchat_request.py
work_wechat_sdk/authority_request.py
work_wechat_sdk/base_request.py
work_wechat_sdk/department_request.py
work_wechat_sdk/message_generics.py
work_wechat_sdk/message_request.py
work_wechat_sdk/mixin.py
work_wechat_sdk/tag_request.py
work_wechat_sdk/url_settings.py
work_wechat_sdk/user_request.py
work_wechat_sdk.egg-info/PKG-INFO
work_wechat_sdk.egg-info/SOURCES.txt
work_wechat_sdk.egg-info/dependency_links.txt
work_wechat_sdk.egg-info/requires.txt
work_wechat_sdk.egg-info/top_level.txt